LICENSE.md
README.md
flake8_sqlalchemy/__init__.py
flake8_sqlalchemy/checkers/__init__.py
flake8_sqlalchemy/checkers/_base.py
flake8_sqlalchemy/checkers/column_comment.py
flake8_sqlalchemy/checkers/import_alias.py
flake8_sqlalchemy/issue.py
flake8_sqlalchemy/plugin.py
flake8_sqlalchemy/py.typed
flake8_sqlalchemy-0.2.0.dist-info/LICENSE.md
flake8_sqlalchemy-0.2.0.dist-info/METADATA
flake8_sqlalchemy-0.2.0.dist-info/WHEEL
flake8_sqlalchemy-0.2.0.dist-info/entry_points.txt
flake8_sqlalchemy-0.2.0.dist-info/RECORD
