Metadata-Version: 2.1
Name: flake8-sqlalchemy
Version: 0.2.0
Summary: A flake8 plugin to detect issues with SQLAlchemy code
Home-page: https://github.com/miketheman/flake8-sqlalchemy
License: MIT
Keywords: flake8,lint,sqlalchemy
Author: Mike Fiedler
Author-email: miketheman@gmail.com
Requires-Python: >=3.8.1,<4.0.0
Classifier: Development Status :: 3 - Alpha
Classifier: Framework :: Flake8
Classifier: Intended Audience :: Developers
Classifier: License :: OSI Approved :: MIT License
Classifier: Natural Language :: English
Classifier: Operating System :: OS Independent
Classifier: Programming Language :: Python :: 3
Classifier: Programming Language :: Python :: 3.9
Classifier: Programming Language :: Python :: 3.10
Classifier: Programming Language :: Python :: 3.11
Classifier: Programming Language :: Python :: 3.8
Classifier: Topic :: Software Development :: Libraries :: Python Modules
Classifier: Topic :: Software Development :: Quality Assurance
Classifier: Topic :: Software Development :: Testing
Classifier: Topic :: Utilities
Classifier: Typing :: Typed
Requires-Dist: flake8 (>=6.0,<7.0)
Project-URL: Repository, https://github.com/miketheman/flake8-sqlalchemy
